ssh_bastion/cli.py
ssh_bastion/config.py
ssh_bastion/core.py
ssh_bastion/misc.py
ssh_bastion-0.1.3.dist-info/LICENSE
ssh_bastion-0.1.3.dist-info/METADATA
ssh_bastion-0.1.3.dist-info/WHEEL
ssh_bastion-0.1.3.dist-info/entry_points.txt
ssh_bastion-0.1.3.dist-info/top_level.txt
ssh_bastion-0.1.3.dist-info/RECORD
