Metadata-Version: 2.1
Name: ssh-bastion
Version: 0.1.3
Summary: SSH proxy server.
Home-page: https://github.com/yxc890123/ssh-bastion
Author: yxc890123
License: Apache 2.0
Classifier: License :: OSI Approved :: Apache Software License
Classifier: Operating System :: POSIX :: Linux
Classifier: Programming Language :: Python :: 3
Requires-Python: >=3.6
License-File: LICENSE
Requires-Dist: paramiko
Requires-Dist: python-pam
Requires-Dist: six
